{
  "subject": {
    "code": "ARTS90010",
    "period": "semester_1",
    "_classList": [
      {
        "description": "Seminar 1",
        "day": 3,
        "start": 12,
        "finish": 14,
        "weeks": [
          10,
          12,
          14,
          17,
          19,
          21
        ],
        "type": "Mandatory",
        "online": false,
        "subjectCode": "ARTS90010",
        "codes": [
          "ARTS90010/U/1/SM1/S01/01"
        ],
        "locations": [
          "PAR-Old Arts-116 (CLS4)"
        ],
        "classCode": {
          "number": 1,
          "type": "S"
        },
        "streamNumber": 1
      }
    ],
    "_irregularClasses": [],
    "_mandatoryClasses": [
      {
        "description": "Seminar 1",
        "day": 3,
        "start": 12,
        "finish": 14,
        "weeks": [
          10,
          12,
          14,
          17,
          19,
          21
        ],
        "type": "Mandatory",
        "online": false,
        "subjectCode": "ARTS90010",
        "codes": [
          "ARTS90010/U/1/SM1/S01/01"
        ],
        "locations": [
          "PAR-Old Arts-116 (CLS4)"
        ],
        "classCode": {
          "number": 1,
          "type": "S"
        },
        "streamNumber": 1
      }
    ],
    "_regularClasses": [],
    "_streamContainers": [],
    "_weirdStreamContainers": [],
    "_weekendClasses": false
  },
  "timestamp": "2023-01-25T09:39:30.098Z"
}