{
  "subject": {
    "code": "EDUC91032",
    "period": "summer_term",
    "_classList": [],
    "_irregularClasses": [],
    "_mandatoryClasses": [
      {
        "description": "Seminar 1",
        "day": 0,
        "start": 10,
        "finish": 12,
        "weeks": [
          4
        ],
        "type": "Mandatory",
        "online": true,
        "subjectCode": "EDUC91032",
        "codes": [
          "EDUC91032/U/1/SUM/S01/01"
        ],
        "locations": [
          "online"
        ],
        "classCode": {
          "number": 1,
          "type": "S"
        },
        "streamNumber": 1
      },
      {
        "description": "Seminar 2",
        "day": 0,
        "start": 14,
        "finish": 16,
        "weeks": [
          4
        ],
        "type": "Mandatory",
        "online": true,
        "subjectCode": "EDUC91032",
        "codes": [
          "EDUC91032/U/1/SUM/S02/01"
        ],
        "locations": [
          "online"
        ],
        "classCode": {
          "number": 2,
          "type": "S"
        },
        "streamNumber": 1
      },
      {
        "description": "Seminar 3",
        "day": 1,
        "start": 10,
        "finish": 12,
        "weeks": [
          4
        ],
        "type": "Mandatory",
        "online": true,
        "subjectCode": "EDUC91032",
        "codes": [
          "EDUC91032/U/1/SUM/S03/01"
        ],
        "locations": [
          "online"
        ],
        "classCode": {
          "number": 3,
          "type": "S"
        },
        "streamNumber": 1
      },
      {
        "description": "Seminar 4",
        "day": 1,
        "start": 14,
        "finish": 16,
        "weeks": [
          4
        ],
        "type": "Mandatory",
        "online": true,
        "subjectCode": "EDUC91032",
        "codes": [
          "EDUC91032/U/1/SUM/S04/01"
        ],
        "locations": [
          "online"
        ],
        "classCode": {
          "number": 4,
          "type": "S"
        },
        "streamNumber": 1
      },
      {
        "description": "Seminar 5",
        "day": 4,
        "start": 10,
        "finish": 12,
        "weeks": [
          4
        ],
        "type": "Mandatory",
        "online": true,
        "subjectCode": "EDUC91032",
        "codes": [
          "EDUC91032/U/1/SUM/S05/01"
        ],
        "locations": [
          "online"
        ],
        "classCode": {
          "number": 5,
          "type": "S"
        },
        "streamNumber": 1
      },
      {
        "description": "Seminar 6",
        "day": 4,
        "start": 14,
        "finish": 16,
        "weeks": [
          4
        ],
        "type": "Mandatory",
        "online": true,
        "subjectCode": "EDUC91032",
        "codes": [
          "EDUC91032/U/1/SUM/S06/01"
        ],
        "locations": [
          "online"
        ],
        "classCode": {
          "number": 6,
          "type": "S"
        },
        "streamNumber": 1
      }
    ],
    "_regularClasses": [],
    "_streamContainers": [
      {
        "streams": [
          {
            "type": "L",
            "classes": [
              {
                "description": "Lecture 1",
                "day": 0,
                "start": 9,
                "finish": 10,
                "weeks": [
                  4
                ],
                "type": "Stream",
                "online": true,
                "subjectCode": "EDUC91032",
                "codes": [
                  "EDUC91032/U/1/SUM/L01/01"
                ],
                "locations": [
                  "online"
                ],
                "classCode": {
                  "number": 1,
                  "type": "L"
                },
                "streamNumber": 1
              },
              {
                "description": "Lecture 2",
                "day": 0,
                "start": 13,
                "finish": 14,
                "weeks": [
                  4
                ],
                "type": "Stream",
                "online": true,
                "subjectCode": "EDUC91032",
                "codes": [
                  "EDUC91032/U/1/SUM/L02/01"
                ],
                "locations": [
                  "online"
                ],
                "classCode": {
                  "number": 2,
                  "type": "L"
                },
                "streamNumber": 1
              },
              {
                "description": "Lecture 3",
                "day": 1,
                "start": 9,
                "finish": 10,
                "weeks": [
                  4
                ],
                "type": "Stream",
                "online": true,
                "subjectCode": "EDUC91032",
                "codes": [
                  "EDUC91032/U/1/SUM/L03/01"
                ],
                "locations": [
                  "online"
                ],
                "classCode": {
                  "number": 3,
                  "type": "L"
                },
                "streamNumber": 1
              },
              {
                "description": "Lecture 4",
                "day": 1,
                "start": 13,
                "finish": 14,
                "weeks": [
                  4
                ],
                "type": "Stream",
                "online": true,
                "subjectCode": "EDUC91032",
                "codes": [
                  "EDUC91032/U/1/SUM/L04/01"
                ],
                "locations": [
                  "online"
                ],
                "classCode": {
                  "number": 4,
                  "type": "L"
                },
                "streamNumber": 1
              },
              {
                "description": "Lecture 5",
                "day": 4,
                "start": 9,
                "finish": 10,
                "weeks": [
                  4
                ],
                "type": "Stream",
                "online": true,
                "subjectCode": "EDUC91032",
                "codes": [
                  "EDUC91032/U/1/SUM/L05/01"
                ],
                "locations": [
                  "online"
                ],
                "classCode": {
                  "number": 5,
                  "type": "L"
                },
                "streamNumber": 1
              },
              {
                "description": "Lecture 6",
                "day": 4,
                "start": 13,
                "finish": 14,
                "weeks": [
                  4
                ],
                "type": "Stream",
                "online": true,
                "subjectCode": "EDUC91032",
                "codes": [
                  "EDUC91032/U/1/SUM/L06/01"
                ],
                "locations": [
                  "online"
                ],
                "classCode": {
                  "number": 6,
                  "type": "L"
                },
                "streamNumber": 1
              }
            ],
            "streamNumbers": [
              1
            ]
          }
        ],
        "type": "L",
        "name": "Lecture"
      }
    ],
    "_weirdStreamContainers": [],
    "_weekendClasses": false
  },
  "timestamp": "2023-01-25T09:40:21.293Z"
}