{
  "subject": {
    "code": "FOOD30010",
    "period": "semester_2",
    "_classList": [
      {
        "description": "Tutorial 1",
        "day": 4,
        "start": 10,
        "finish": 11,
        "weeks": [
          30,
          31,
          32,
          33,
          34,
          35,
          36,
          37,
          38,
          40,
          41,
          42
        ],
        "type": "Variable",
        "online": false,
        "subjectCode": "FOOD30010",
        "codes": [
          "FOOD30010/U/1/SM2/T01/01"
        ],
        "locations": [
          "PAR-Medical-E307 (Frederic Wood Jones)"
        ],
        "classCode": {
          "number": 1,
          "type": "T"
        },
        "streamNumber": 1
      },
      {
        "description": "Tutorial 1",
        "day": 4,
        "start": 11,
        "finish": 12,
        "weeks": [
          30,
          31,
          32,
          33,
          34,
          35,
          36,
          37,
          38,
          40,
          41,
          42
        ],
        "type": "Variable",
        "online": false,
        "subjectCode": "FOOD30010",
        "codes": [
          "FOOD30010/U/1/SM2/T01/02"
        ],
        "locations": [
          "PAR-Medical-E307 (Frederic Wood Jones)"
        ],
        "classCode": {
          "number": 1,
          "type": "T"
        },
        "streamNumber": 2
      },
      {
        "description": "Tutorial 1",
        "day": 4,
        "start": 12,
        "finish": 13,
        "weeks": [
          30,
          31,
          32,
          33,
          34,
          35,
          36,
          37,
          38,
          40,
          41,
          42
        ],
        "type": "Variable",
        "online": false,
        "subjectCode": "FOOD30010",
        "codes": [
          "FOOD30010/U/1/SM2/T01/03"
        ],
        "locations": [
          "PAR-Medical-E307 (Frederic Wood Jones)"
        ],
        "classCode": {
          "number": 1,
          "type": "T"
        },
        "streamNumber": 3
      },
      {
        "description": "Tutorial 1",
        "day": 4,
        "start": 13,
        "finish": 14,
        "weeks": [
          30,
          31,
          32,
          33,
          34,
          35,
          36,
          37,
          38,
          40,
          41,
          42
        ],
        "type": "Variable",
        "online": false,
        "subjectCode": "FOOD30010",
        "codes": [
          "FOOD30010/U/1/SM2/T01/04"
        ],
        "locations": [
          "PAR-Medical-E307 (Frederic Wood Jones)"
        ],
        "classCode": {
          "number": 1,
          "type": "T"
        },
        "streamNumber": 4
      }
    ],
    "_irregularClasses": [],
    "_mandatoryClasses": [],
    "_regularClasses": [
      {
        "description": "Tutorial 1",
        "day": 4,
        "start": 10,
        "finish": 11,
        "weeks": [
          30,
          31,
          32,
          33,
          34,
          35,
          36,
          37,
          38,
          40,
          41,
          42
        ],
        "type": "Variable",
        "online": false,
        "subjectCode": "FOOD30010",
        "codes": [
          "FOOD30010/U/1/SM2/T01/01"
        ],
        "locations": [
          "PAR-Medical-E307 (Frederic Wood Jones)"
        ],
        "classCode": {
          "number": 1,
          "type": "T"
        },
        "streamNumber": 1
      },
      {
        "description": "Tutorial 1",
        "day": 4,
        "start": 11,
        "finish": 12,
        "weeks": [
          30,
          31,
          32,
          33,
          34,
          35,
          36,
          37,
          38,
          40,
          41,
          42
        ],
        "type": "Variable",
        "online": false,
        "subjectCode": "FOOD30010",
        "codes": [
          "FOOD30010/U/1/SM2/T01/02"
        ],
        "locations": [
          "PAR-Medical-E307 (Frederic Wood Jones)"
        ],
        "classCode": {
          "number": 1,
          "type": "T"
        },
        "streamNumber": 2
      },
      {
        "description": "Tutorial 1",
        "day": 4,
        "start": 12,
        "finish": 13,
        "weeks": [
          30,
          31,
          32,
          33,
          34,
          35,
          36,
          37,
          38,
          40,
          41,
          42
        ],
        "type": "Variable",
        "online": false,
        "subjectCode": "FOOD30010",
        "codes": [
          "FOOD30010/U/1/SM2/T01/03"
        ],
        "locations": [
          "PAR-Medical-E307 (Frederic Wood Jones)"
        ],
        "classCode": {
          "number": 1,
          "type": "T"
        },
        "streamNumber": 3
      },
      {
        "description": "Tutorial 1",
        "day": 4,
        "start": 13,
        "finish": 14,
        "weeks": [
          30,
          31,
          32,
          33,
          34,
          35,
          36,
          37,
          38,
          40,
          41,
          42
        ],
        "type": "Variable",
        "online": false,
        "subjectCode": "FOOD30010",
        "codes": [
          "FOOD30010/U/1/SM2/T01/04"
        ],
        "locations": [
          "PAR-Medical-E307 (Frederic Wood Jones)"
        ],
        "classCode": {
          "number": 1,
          "type": "T"
        },
        "streamNumber": 4
      }
    ],
    "_streamContainers": [
      {
        "streams": [
          {
            "type": "L",
            "classes": [
              {
                "description": "Lecture 1",
                "day": 0,
                "start": 14.25,
                "finish": 15.25,
                "weeks": [
                  30,
                  31,
                  32,
                  33,
                  34,
                  35,
                  36,
                  37,
                  38,
                  40,
                  41,
                  42
                ],
                "type": "Stream",
                "online": false,
                "subjectCode": "FOOD30010",
                "codes": [
                  "FOOD30010/U/1/SM2/L01/01"
                ],
                "locations": [
                  "PAR-Biosciences 4-G003 (Agar Theatre)"
                ],
                "classCode": {
                  "number": 1,
                  "type": "L"
                },
                "streamNumber": 1
              },
              {
                "description": "Lecture 2",
                "day": 1,
                "start": 9,
                "finish": 10,
                "weeks": [
                  30,
                  31,
                  32,
                  33,
                  34,
                  35,
                  36,
                  37,
                  38,
                  40,
                  41,
                  42
                ],
                "type": "Stream",
                "online": false,
                "subjectCode": "FOOD30010",
                "codes": [
                  "FOOD30010/U/1/SM2/L02/01"
                ],
                "locations": [
                  "PAR-Biosciences 2-124 (Turner Theatre)"
                ],
                "classCode": {
                  "number": 2,
                  "type": "L"
                },
                "streamNumber": 1
              },
              {
                "description": "Lecture 3",
                "day": 1,
                "start": 10,
                "finish": 11,
                "weeks": [
                  30,
                  31,
                  32,
                  33,
                  34,
                  35,
                  36,
                  37,
                  38,
                  40,
                  41,
                  42
                ],
                "type": "Stream",
                "online": false,
                "subjectCode": "FOOD30010",
                "codes": [
                  "FOOD30010/U/1/SM2/L03/01"
                ],
                "locations": [
                  "PAR-Biosciences 2-124 (Turner Theatre)"
                ],
                "classCode": {
                  "number": 3,
                  "type": "L"
                },
                "streamNumber": 1
              }
            ],
            "streamNumbers": [
              1
            ]
          },
          {
            "type": "L",
            "classes": [
              {
                "description": "Lecture 1",
                "day": 0,
                "start": 14.25,
                "finish": 15.25,
                "weeks": [
                  30,
                  31,
                  32,
                  33,
                  34,
                  35,
                  36,
                  37,
                  38,
                  40,
                  41,
                  42
                ],
                "type": "Stream",
                "online": true,
                "subjectCode": "FOOD30010",
                "codes": [
                  "FOOD30010/U/1/SM2/L01/02"
                ],
                "locations": [
                  "online"
                ],
                "classCode": {
                  "number": 1,
                  "type": "L"
                },
                "streamNumber": 2
              },
              {
                "description": "Lecture 2",
                "day": 1,
                "start": 9,
                "finish": 10,
                "weeks": [
                  30,
                  31,
                  32,
                  33,
                  34,
                  35,
                  36,
                  37,
                  38,
                  40,
                  41,
                  42
                ],
                "type": "Stream",
                "online": true,
                "subjectCode": "FOOD30010",
                "codes": [
                  "FOOD30010/U/1/SM2/L02/02"
                ],
                "locations": [
                  "online"
                ],
                "classCode": {
                  "number": 2,
                  "type": "L"
                },
                "streamNumber": 2
              },
              {
                "description": "Lecture 3",
                "day": 1,
                "start": 10,
                "finish": 11,
                "weeks": [
                  30,
                  31,
                  32,
                  33,
                  34,
                  35,
                  36,
                  37,
                  38,
                  40,
                  41,
                  42
                ],
                "type": "Stream",
                "online": true,
                "subjectCode": "FOOD30010",
                "codes": [
                  "FOOD30010/U/1/SM2/L03/02"
                ],
                "locations": [
                  "online"
                ],
                "classCode": {
                  "number": 3,
                  "type": "L"
                },
                "streamNumber": 2
              }
            ],
            "streamNumbers": [
              2
            ]
          }
        ],
        "type": "L",
        "name": "Lecture"
      }
    ],
    "_weirdStreamContainers": [],
    "_weekendClasses": false
  },
  "timestamp": "2023-01-25T09:40:48.836Z"
}